setup.py
luminance/__init__.py
luminance/escape2.py
luminance/escape3.py
luminance/lib27.py
luminance/lib3.py
luminance/lib334.py
luminance/lib335.py
luminance.egg-info/PKG-INFO
luminance.egg-info/SOURCES.txt
luminance.egg-info/dependency_links.txt
luminance.egg-info/top_level.txt