Metadata-Version: 2.1
Name: luminance
Version: 0.1.4
Summary: Luminance is a library for working with user output and console input
Home-page: https://github.com/reslaid/luminance
Author: Artem Reslaid
License: MIT
Platform: UNKNOWN
Classifier: License :: OSI Approved :: MIT License
Classifier: Programming Language :: Python :: 2.7
Classifier: Programming Language :: Python :: 3.3
Classifier: Programming Language :: Python :: 3.4
Classifier: Programming Language :: Python :: 3.5
Classifier: Programming Language :: Python :: 3.6
Classifier: Programming Language :: Python :: 3.7
Classifier: Programming Language :: Python :: 3.8
